spwla/__init__.py
spwla/__main__.py
spwla/_version.py
spwla/cli.py
spwla/resistivity.py
spwla-0.0.2.dist-info/AUTHORS.rst
spwla-0.0.2.dist-info/LICENSE
spwla-0.0.2.dist-info/METADATA
spwla-0.0.2.dist-info/WHEEL
spwla-0.0.2.dist-info/entry_points.txt
spwla-0.0.2.dist-info/top_level.txt
spwla-0.0.2.dist-info/RECORD
