Metadata-Version: 2.1
Name: spwla
Version: 0.0.2
Summary: A Python package by SPWLA for educational purpose
Home-page: https://github.com/lianglin0310/spwla
Author: Lin Liang
Author-email: lianglin0310@yahoo.com
License: MIT
Project-URL: Issue Tracker, https://github.com/lianglin0310/spwla/issues
Project-URL: Documentation, https://spwla.readthedocs.io/
Project-URL: Changelog, https://spwla.readthedocs.io/en/latest/changelog.html
Platform: UNKNOWN
Classifier: Development Status :: 5 - Production/Stable
Classifier: Intended Audience :: Developers
Classifier: License :: OSI Approved :: MIT License
Classifier: Operating System :: Unix
Classifier: Operating System :: POSIX
Classifier: Operating System :: Microsoft :: Windows
Classifier: Programming Language :: Python
Classifier: Programming Language :: Python :: 2.7
Classifier: Programming Language :: Python :: 3
Classifier: Programming Language :: Python :: 3.5
Classifier: Programming Language :: Python :: 3.6
Classifier: Programming Language :: Python :: 3.7
Classifier: Programming Language :: Python :: 3.8
Classifier: Programming Language :: Python :: Implementation :: CPython
Classifier: Programming Language :: Python :: Implementation :: PyPy
Classifier: Topic :: Utilities
Requires-Python: >=2.7, !=3.0.*, !=3.1.*, !=3.2.*, !=3.3.*, !=3.4.*
